{
  "mutations": [
    {
      "create": {
        "_type": "post",
        "title": "You probably think topology is just abstract math from college. Wrong.",
        "slug": {
          "_type": "slug",
          "current": "topology-powering-modern-tech"
        },
        "excerpt": "Topology isn’t just abstract math — it powers Kubernetes, neural networks, blockchain, DNA computing, and mesh networks.",
        "publishedAt": "2025-04-05T10:00:00Z",
        "updatedAt": "2025-04-05T10:00:00Z",
        "status": "published",
        "featured": true,
        "sticky": false,
        "body": [
          {
            "_key": "intro-1",
            "_type": "block",
            "style": "normal",
            "children": [
              {
                "_key": "intro-text-1",
                "_type": "span",
                "text": "You probably think topology is just abstract math from college. Wrong. It's secretly running some of the most cutting-edge technologies you use every day. Here are five technologies where topology isn't just involved—it's absolutely critical.",
                "marks": []
              }
            ]
          },
          {
            "_key": "heading-k8s",
            "_type": "block",
            "style": "h2",
            "children": [
              {
                "_key": "k8s-title",
                "_type": "span",
                "text": "1. Kubernetes: Your Container Orchestrator is a Topology Master",
                "marks": []
              }
            ]
          },
          {
            "_key": "k8s-desc-1",
            "_type": "block",
            "style": "normal",
            "children": [
              {
                "_key": "k8s-p1",
                "_type": "span",
                "text": "Every time you deploy a microservice, Kubernetes is solving complex topology problems behind the scenes. It's not just scheduling containers—it's mapping the relationships between pods, services, and nodes in a dynamic topological space.",
                "marks": []
              }
            ]
          },
          {
            "_key": "k8s-list-1",
            "_type": "block",
            "style": "bullet",
            "level": 1,
            "listItem": "bullet",
            "children": [
              {
                "_key": "k8s-li1",
                "_type": "span",
                "text": "Service Mesh Integration: Kubernetes works with service meshes like Istio that create topological maps of service-to-service communication",
                "marks": []
              },
              {
                "_key": "k8s-li2",
                "_type": "span",
                "text": "Pod Network Topology: Each pod gets its own IP address, and Kubernetes maintains the topological relationships between pods across nodes",
                "marks": []
              },
              {
                "_key": "k8s-li3",
                "_type": "span",
                "text": "Cluster Topology Awareness: Kubernetes uses topology spread constraints to understand rack awareness, zone distribution, and failure domains",
                "marks": []
              },
              {
                "_key": "k8s-li4",
                "_type": "span",
                "text": "CNI (Container Network Interface): The networking layer creates overlay networks that are essentially dynamic topological structures",
                "marks": []
              }
            ]
          },
          {
            "_key": "k8s-desc-2",
            "_type": "block",
            "style": "normal",
            "children": [
              {
                "_key": "k8s-p2",
                "_type": "span",
                "text": "When you scale a deployment, Kubernetes isn't just spinning up more containers—it's recalculating the optimal topological arrangement of your entire system based on resource constraints, network latency, and failure tolerance.",
                "marks": []
              }
            ]
          },
          {
            "_key": "heading-nn",
            "_type": "block",
            "style": "h2",
            "children": [
              {
                "_key": "nn-title",
                "_type": "span",
                "text": "2. Neural Networks: Deep Learning is Applied Topology",
                "marks": []
              }
            ]
          },
          {
            "_key": "nn-desc-1",
            "_type": "block",
            "style": "normal",
            "children": [
              {
                "_key": "nn-p1",
                "_type": "span",
                "text": "Your AI models are topology computers in disguise. Topological deep learning (TDL) is a research field that extends deep learning to handle complex, non-Euclidean data structures, but even traditional neural networks are fundamentally topological.",
                "marks": []
              }
            ]
          },
          {
            "_key": "nn-list-1",
            "_type": "block",
            "style": "bullet",
            "level": 1,
            "listItem": "bullet",
            "children": [
              {
                "_key": "nn-li1",
                "_type": "span",
                "text": "Manifold Learning: Topological properties of data, such as links, may make it impossible to linearly separate classes using low-dimensional networks, regardless of depth",
                "marks": []
              },
              {
                "_key": "nn-li2",
                "_type": "span",
                "text": "Network Architecture: The connections between layers create topological spaces where information flows",
                "marks": []
              },
              {
                "_key": "nn-li3",
                "_type": "span",
                "text": "ReLU Activation Mystery: A nonsmooth activation function like ReLU outperforms a smooth one like hyperbolic tangent because it preserves certain topological properties during backpropagation",
                "marks": []
              },
              {
                "_key": "nn-li4",
                "_type": "span",
                "text": "Persistent Homology: TDA provides insight into data shape; it obtains global descriptions of multi-dimensional data whilst exhibiting robustness to deformation and noise",
                "marks": []
              }
            ]
          },
          {
            "_key": "nn-code",
            "_type": "code",
            "code": "import torch\nmodel = torch.nn.Sequential(\n    torch.nn.Linear(784, 128),\n    torch.nn.ReLU(),\n    torch.nn.Linear(128, 10)\n)",
            "language": "python"
          },
          {
            "_key": "nn-desc-2",
            "_type": "block",
            "style": "normal",
            "children": [
              {
                "_key": "nn-p2",
                "_type": "span",
                "text": "Modern deep learning frameworks like PyTorch and TensorFlow are essentially topology manipulation engines, transforming data through high-dimensional topological spaces.",
                "marks": []
              }
            ]
          },
          {
            "_key": "heading-bc",
            "_type": "block",
            "style": "h2",
            "children": [
              {
                "_key": "bc-title",
                "_type": "span",
                "text": "3. Blockchain Networks: Decentralized Topology in Action",
                "marks": []
              }
            ]
          },
          {
            "_key": "bc-desc-1",
            "_type": "block",
            "style": "normal",
            "children": [
              {
                "_key": "bc-p1",
                "_type": "span",
                "text": "Blockchain isn't just a distributed ledger—it's a constantly evolving topological network where the shape of connections determines security, speed, and consensus.",
                "marks": []
              }
            ]
          },
          {
            "_key": "bc-list-1",
            "_type": "block",
            "style": "bullet",
            "level": 1,
            "listItem": "bullet",
            "children": [
              {
                "_key": "bc-li1",
                "_type": "span",
                "text": "P2P Network Topology: Each node maintains connections to multiple peers, creating a mesh-like topological structure",
                "marks": []
              },
              {
                "_key": "bc-li2",
                "_type": "span",
                "text": "Consensus Mechanisms: Proof-of-Work and Proof-of-Stake algorithms rely on the topology of the network to achieve distributed consensus",
                "marks": []
              },
              {
                "_key": "bc-li3",
                "_type": "span",
                "text": "Mesh Network Integration: While mesh networking makes connecting to the Internet easy and affordable, blockchain on top of mesh networks makes Internet access profitable by enabling bandwidth-sharing for crypto-tokens",
                "marks": []
              },
              {
                "_key": "bc-li4",
                "_type": "span",
                "text": "Byzantine Fault Tolerance: The topology must be resilient enough to handle malicious nodes while maintaining network integrity",
                "marks": []
              }
            ]
          },
          {
            "_key": "bc-desc-2",
            "_type": "block",
            "style": "normal",
            "children": [
              {
                "_key": "bc-p2",
                "_type": "span",
                "text": "Lightning Network and other Layer 2 solutions create additional topological layers on top of the base blockchain, optimizing for different network properties.",
                "marks": []
              }
            ]
          },
          {
            "_key": "heading-dna",
            "_type": "block",
            "style": "h2",
            "children": [
              {
                "_key": "dna-title",
                "_type": "span",
                "text": "4. DNA Computing: Biological Topology Meets Digital Logic",
                "marks": []
              }
            ]
          },
          {
            "_key": "dna-desc-1",
            "_type": "block",
            "style": "normal",
            "children": [
              {
                "_key": "dna-p1",
                "_type": "span",
                "text": "This one will blow your mind. Scientists from North Carolina State University and Johns Hopkins University developed a system for conducting storage, memory, and processing functions using DNA-based computers, and it's fundamentally based on molecular topology.",
                "marks": []
              }
            ]
          },
          {
            "_key": "dna-list-1",
            "_type": "block",
            "style": "bullet",
            "level": 1,
            "listItem": "bullet",
            "children": [
              {
                "_key": "dna-li1",
                "_type": "span",
                "text": "Molecular Topology: DNA strands fold into specific 3D shapes that determine computational behavior",
                "marks": []
              },
              {
                "_key": "dna-li2",
                "_type": "span",
                "text": "Network Protocols: Biological cells can transmit, process and receive chemically encoded data in the same way as network devices transmit, process, and receive digitally encoded data",
                "marks": []
              },
              {
                "_key": "dna-li3",
                "_type": "span",
                "text": "Blockchain Integration: DNA computing is the execution of computations using natural molecules, especially DNA. DNA gaps above silicon because of massive parallelism, size and storage density",
                "marks": []
              },
              {
                "_key": "dna-li4",
                "_type": "span",
                "text": "Massive Parallelism: The topological structure of DNA allows for thousands of computations to happen simultaneously in a single test tube",
                "marks": []
              }
            ]
          },
          {
            "_key": "dna-desc-2",
            "_type": "block",
            "style": "normal",
            "children": [
              {
                "_key": "dna-p2",
                "_type": "span",
                "text": "Companies are already exploring DNA storage for data centers, where the topology of molecular structures determines data retrieval speed and accuracy.",
                "marks": []
              }
            ]
          },
          {
            "_key": "heading-mesh",
            "_type": "block",
            "style": "h2",
            "children": [
              {
                "_key": "mesh-title",
                "_type": "span",
                "text": "5. Mesh Networks: Self-Organizing Topological Intelligence",
                "marks": []
              }
            ]
          },
          {
            "_key": "mesh-desc-1",
            "_type": "block",
            "style": "normal",
            "children": [
              {
                "_key": "mesh-p1",
                "_type": "span",
                "text": "Your WiFi router might be part of a mesh network, and if it is, it's constantly recalculating optimal topological paths for your data.",
                "marks": []
              }
            ]
          },
          {
            "_key": "mesh-list-1",
            "_type": "block",
            "style": "bullet",
            "level": 1,
            "listItem": "bullet",
            "children": [
              {
                "_key": "mesh-li1",
                "_type": "span",
                "text": "Dynamic Self-Organization: Mesh networks dynamically self-organize and self-configure, which can reduce installation overhead",
                "marks": []
              },
              {
                "_key": "mesh-li2",
                "_type": "span",
                "text": "Topological Resilience: Mesh network topologies create multiple routes for information to travel among connected nodes. This approach increases the resilience of the network in case of a node or connection failure",
                "marks": []
              },
              {
                "_key": "mesh-li3",
                "_type": "span",
                "text": "Multi-Path Routing: Each packet can take different topological paths through the network",
                "marks": []
              },
              {
                "_key": "mesh-li4",
                "_type": "span",
                "text": "Blockchain Integration: A comprehensive blockchain-based framework for commercialized mesh networks is proposed. The framework (1) manages the routing requests, (2) selects mesh routers with high-quality and low routing cost",
                "marks": []
              }
            ]
          },
          {
            "_key": "mesh-desc-2",
            "_type": "block",
            "style": "normal",
            "children": [
              {
                "_key": "mesh-p2",
                "_type": "span",
                "text": "Modern mesh networks like Starlink's satellite constellation are constantly solving topology optimization problems to route data through the most efficient paths in 3D space.",
                "marks": []
              }
            ]
          },
          {
            "_key": "heading-conclusion",
            "_type": "block",
            "style": "h2",
            "children": [
              {
                "_key": "conclusion-title",
                "_type": "span",
                "text": "The Bottom Line",
                "marks": []
              }
            ]
          },
          {
            "_key": "conclusion-desc",
            "_type": "block",
            "style": "normal",
            "children": [
              {
                "_key": "conclusion-text",
                "_type": "span",
                "text": "Topology isn't abstract math—it's the hidden engine powering the technologies reshaping our world. From the moment you deploy a Docker container to the way your AI model processes images, topological principles are working behind the scenes to make these systems fast, reliable, and scalable.\n\nNext time someone says topology is \"just theory,\" remind them that their Netflix stream, crypto wallet, and smart home are all powered by applied topology running 24/7.",
                "marks": []
              }
            ]
          }
        ],
        "readingTime": 7,
        "seo": {
          "_type": "seo",
          "metaTitle": "How Topology Powers Kubernetes, AI, Blockchain & More | Hidden Math Behind Tech",
          "metaDescription": "Discover how topology secretly powers technologies like Kubernetes orchestration, deep learning, and mesh networking.",
          "canonicalUrl": "https://example.com/topology-powering-modern-tech"
        }
      }
    }
  ]
}
